librian/__init__.py
librian/__main__.py
librian/librian_util/加載器.py
librian/librian_util/文件.py
librian/librian_util/路徑.py
librian/librian本體/librian.py
librian/librian本體/導出文件.py
librian/librian本體/山彥.py
librian/librian本體/幻象.py
librian/librian本體/測試.py
librian/librian本體/環境.py
librian/librian本體/窗口.py
librian/librian本體/配置.yaml
librian/librian本體/librian虛擬機/命令.py
librian/librian本體/librian虛擬機/立繪.py
librian/librian本體/librian虛擬機/箱庭.py
librian/librian本體/librian虛擬機/虛擬機環境.py
librian/librian本體/librian虛擬機/角色.py
librian/librian本體/librian虛擬機/讀者.py
librian/librian本體/librian虛擬機/鏡頭.py
librian/librian本體/前端/adv.html
librian/librian本體/前端/adv.ptml
librian/librian本體/前端/package-lock.json
librian/librian本體/前端/package.json
librian/librian本體/前端/webpack.config.js
librian/librian本體/前端/dist/NotoSerifSC-SemiBold.otf
librian/librian本體/前端/dist/bundle.js
librian/librian本體/前端/dist/t0.png
librian/librian本體/前端/dist/紙背景花紋.jpg
librian/librian本體/前端/dist/紙背景花紋.webp
librian/librian本體/前端/dist/紙背景花紋模糊.jpg
librian/librian本體/前端/dist/紙背景花紋模糊.webp
librian/librian本體/前端/黑科技/font-awesome-4.7.0/HELP-US-OUT.txt
librian/librian本體/前端/黑科技/font-awesome-4.7.0/css/font-awesome.css
librian/librian本體/前端/黑科技/font-awesome-4.7.0/css/font-awesome.min.css
librian/librian本體/前端/黑科技/font-awesome-4.7.0/fonts/FontAwesome.otf
librian/librian本體/前端/黑科技/font-awesome-4.7.0/fonts/fontawesome-webfont.eot
librian/librian本體/前端/黑科技/font-awesome-4.7.0/fonts/fontawesome-webfont.svg
librian/librian本體/前端/黑科技/font-awesome-4.7.0/fonts/fontawesome-webfont.ttf
librian/librian本體/前端/黑科技/font-awesome-4.7.0/fonts/fontawesome-webfont.woff
librian/librian本體/前端/黑科技/font-awesome-4.7.0/fonts/fontawesome-webfont.woff2
librian/librian本體/前端/黑科技/font-awesome-4.7.0/less/animated.less
librian/librian本體/前端/黑科技/font-awesome-4.7.0/less/bordered-pulled.less
librian/librian本體/前端/黑科技/font-awesome-4.7.0/less/core.less
librian/librian本體/前端/黑科技/font-awesome-4.7.0/less/fixed-width.less
librian/librian本體/前端/黑科技/font-awesome-4.7.0/less/font-awesome.less
librian-2.0.2.dist-info/LICENSE
librian-2.0.2.dist-info/METADATA
librian-2.0.2.dist-info/WHEEL
librian-2.0.2.dist-info/top_level.txt
librian-2.0.2.dist-info/RECORD
