Metadata-Version: 2.1
Name: librian
Version: 2.0.2
Summary: librian
Home-page: https://github.com/RimoChan/librian
Author: RimoChan
Author-email: the@librian.net
License: UNKNOWN
Platform: UNKNOWN
Classifier: Programming Language :: Python :: 3
Classifier: Operating System :: OS Independent
Requires-Python: >=3.6, <=3.7
Requires-Dist: liber (>=1.0.1)
Requires-Dist: rimo-utils (>=1.4.1)
Requires-Dist: cefpython3 (>=66.0)
Requires-Dist: wxPython (>=4.0.4)
Requires-Dist: cloudpickle (>=1.2.2)
Requires-Dist: opencc (>=1.1.1)
Requires-Dist: PyYAML (>=5.2)
Requires-Dist: fire (>=0.2.1)
Requires-Dist: requests (>=2.24.0)
Requires-Dist: libsass (>=0.20.0)
Requires-Dist: AppKit (>=0.2.8) ; sys_platform == "darwin"
